shedding_hub/__init__.py
shedding_hub/shedding_duration.py
shedding_hub/shedding_peak.py
shedding_hub/stats.py
shedding_hub/util.py
shedding_hub/viz.py
tests/test_data.py
tests/test_shedding_duration.py
tests/test_shedding_peak.py
tests/test_summarize.py
tests/test_util.py
tests/test_viz.py
shedding_hub-0.1.2.dist-info/METADATA
shedding_hub-0.1.2.dist-info/WHEEL
shedding_hub-0.1.2.dist-info/top_level.txt
shedding_hub-0.1.2.dist-info/RECORD
