Metadata-Version: 2.4
Name: shedding-hub
Version: 0.1.2
Summary: Data and statistical models for biomarker shedding.
Requires-Dist: pyaml
Requires-Dist: requests
Requires-Dist: pandas
Requires-Dist: matplotlib
